PaCal-1.6.dist-info/METADATA
PaCal-1.6.dist-info/RECORD
PaCal-1.6.dist-info/WHEEL
PaCal-1.6.dist-info/top_level.txt
pacal/__init__.py
pacal/bary_interp.pyd
pacal/distr.py
pacal/gamma.py
pacal/indeparith.py
pacal/integration.py
pacal/interpolation.py
pacal/params.py
pacal/rv.py
pacal/segments.py
pacal/standard_distr.py
pacal/sympy_utils.py
pacal/utils.py
pacal/vartransforms.py
pacal/depvars/__init__.py
pacal/depvars/copulas.py
pacal/depvars/models.py
pacal/depvars/nddistr.py
pacal/depvars/sparse_grids.py
pacal/examples/Hill_estimator.py
pacal/examples/__init__.py
pacal/examples/central_limit_demo.py
pacal/examples/discrete.py
pacal/examples/extreme_value_demo.py
pacal/examples/functions.py
pacal/examples/measurements.py
pacal/examples/noncentral.py
pacal/examples/order_stats.py
pacal/examples/singularities.py
pacal/examples/dependent/__init__.py
pacal/examples/dependent/depvars_demo.py
pacal/examples/dependent/diffeq_noise.py
pacal/examples/dependent/kalman.py
pacal/examples/dependent/linreg.py
pacal/examples/dependent/sums.py
pacal/examples/dependent/two_variables/__init__.py
pacal/examples/dependent/two_variables/order_stats.py
pacal/examples/dependent/two_variables/regression.py
pacal/examples/dependent/two_variables/resistors.py
pacal/examples/dependent/two_variables/sum_dependent.py
pacal/examples/springer_book/Chapter3_sums.py
pacal/examples/springer_book/Chapter4_products.py
pacal/examples/springer_book/Chapter5_functions.py
pacal/examples/springer_book/Chapter9_applications.py
pacal/examples/springer_book/Chapters678.py
pacal/examples/springer_book/__init__.py
pacal/stats/__init__.py
pacal/stats/distr_est.py
pacal/stats/iid_ops.py
pacal/stats/noncentral_distr.py
