Metadata-Version: 2.1
Name: PaCal
Version: 1.6
Summary: PaCal - ProbAbilistic CALculator
Home-page: http://pacal.sf.net
Author: Szymon Jaroszewicz, Marcin Korzeń
Author-email: s.jaroszewicz@ipipan.waw.pl, mkorzen@wi.zut.edu.pl
License: GNU General Public License V.3 or later
Platform: UNKNOWN
Requires: Python (>=2.7)
Requires: numpy (>=1.6)
Requires: matplotlib (>=1.0)
Requires: Cython
Requires: Sympy (>=0.6.7)
Requires: scipy (>=13.0)
